{"P6": {"labels": ["documentation"], "postTitle": "\u6f2b\u753b\u8f6f\u4ef6\u63a8\u8350", "postUrl": "post/man-hua-ruan-jian-tui-jian.html", "createdDate": "2024-07-26", "dateLabelColor": "#bc4c00"}, "P5": {"labels": ["documentation"], "postTitle": "IOS\u9605\u8bfb\u8f6f\u4ef6\u63a8\u8350", "postUrl": "post/IOS-yue-du-ruan-jian-tui-jian.html", "createdDate": "2024-07-25", "dateLabelColor": "#bc4c00"}, "P4": {"labels": ["documentation"], "postTitle": "Android\u9605\u8bfb\u8f6f\u4ef6\u63a8\u8350", "postUrl": "post/Android-yue-du-ruan-jian-tui-jian.html", "createdDate": "2024-07-25", "dateLabelColor": "#bc4c00"}, "P3": {"labels": ["documentation"], "postTitle": "\u5c0f\u8bf4\u7f51\u7ad9\u63a8\u8350", "postUrl": "post/xiao-shuo-wang-zhan-tui-jian.html", "createdDate": "2024-07-25", "dateLabelColor": "#bc4c00"}, "labelColorDict": {"bug": "#d73a4a", "documentation": "#0075ca", "duplicate": "#cfd3d7", "enhancement": "#a2eeef", "good first issue": "#7057ff", "help wanted": "#008672", "invalid": "#e4e669", "question": "#d876e3", "wontfix": "#ffffff"}}